[
  {
    "field": "PMN33",
    "title": "原始交货日期",
    "width": 100
  },
  {
    "field": "PMN34",
    "title": "原始到厂日期",
    "width": 100
  },
  {
    "field": "PMN35",
    "title": "原始到库日期",
    "width": 100
  },
  {
    "field": "PMN041",
    "title": "品名",
    "width": 100
  },
  {
    "field": "PMNUD04",
    "title": "备注",
    "width": 100
  },
  {
    "field": "PMN04",
    "title": "料件编号",
    "width": 100
  },
  {
    "field": "CJL",
    "title": "未交数量",
    "width": 100
  },
  {
    "field": "PMN16",
    "title": "状况码",
    "width": 100
  },
  {
    "field": "PMNUD05",
    "title": "生产季节",
    "width": 100
  },
  {
    "field": "PMNUD05_DS",
    "title": "生产季节说明",
    "width": 100
  },
  {
    "field": "GEN02Y",
    "title": "结案人员",
    "width": 100
  },
  {
    "field": "PMNUD13",
    "title": "结案日期",
    "width": 100
  },
  {
    "field": "IMA021",
    "title": "规格",
    "width": 100
  },
  {
    "field": "PMN86",
    "title": "计价单位",
    "width": 100
  },
  {
    "field": "PMN24",
    "title": "请购单号",
    "width": 100
  },
  {
    "field": "PMN25",
    "title": "请购单项次",
    "width": 100
  },
  {
    "field": "PMN67",
    "title": "请购部门编号",
    "width": 100
  },
  {
    "field": "GEM02",
    "title": "部门名称",
    "width": 100
  },
  {
    "field": "PMN07",
    "title": "采购单位",
    "width": 100
  },
  {
    "field": "PMN01",
    "title": "采购单号",
    "width": 100
  },
  {
    "field": "PMN20",
    "title": "采购量",
    "width": 100
  },
  {
    "field": "TA_PMN05",
    "title": "阶段",
    "width": 100
  },
  {
    "field": "TA_PMN05_DS",
    "title": "阶段中文说明",
    "width": 100
  },
  {
    "field": "PMN02",
    "title": "项次",
    "width": 100
  }
]